manage.py
home/__init__.py
home/models.py
home/migrations/0001_initial.py
home/migrations/0002_create_homepage.py
home/migrations/__init__.py
mysite/__init__.py
mysite/urls.py
mysite/wsgi.py
mysite/settings/__init__.py
mysite/settings/base.py
mysite/settings/dev.py
mysite/settings/production.py
search/__init__.py
search/views.py
testingen-0.0.0.dist-info/METADATA
testingen-0.0.0.dist-info/WHEEL
testingen-0.0.0.dist-info/top_level.txt
testingen-0.0.0.dist-info/RECORD
